{
    "uvs7:0": "<article id='uvs7' lang='san'>",
    "uvs7:1": "<header>",
    "uvs7:2": "<ul>",
    "uvs7:3": "<li class='division'>{}</li>",
    "uvs7:4": "</ul>",
    "uvs7:5": "<h1>{}</h1>",
    "uvs7:6": "</header>",
    "uvs7:7": "<blockquote class='gatha'>",
    "uvs7:8": "<p>{}<br>",
    "uvs7:9": "{}<br>",
    "uvs7:10": "{}</p>",
    "uvs7:11": "<p>{}<br>",
    "uvs7:12": "{}<br>",
    "uvs7:13": "{}<br>",
    "uvs7:14": "{}</p>",
    "uvs7:15": "<p>{}<br>",
    "uvs7:16": "{}<br>",
    "uvs7:17": "{}<br>",
    "uvs7:18": "{}</p>",
    "uvs7:19": "<p>{}<br>",
    "uvs7:20": "{}<br>",
    "uvs7:21": "{}<br>",
    "uvs7:22": "{}</p>",
    "uvs7:23": "<p>{}<br>",
    "uvs7:24": "{}<br>",
    "uvs7:25": "{}<br>",
    "uvs7:26": "{}</p>",
    "uvs7:27": "<p>{}<br>",
    "uvs7:28": "{}<br>",
    "uvs7:29": "{}<br>",
    "uvs7:30": "{}</p>",
    "uvs7:31": "<p>{}<br>",
    "uvs7:32": "{}<br>",
    "uvs7:33": "{}<br>",
    "uvs7:34": "{}<br>",
    "uvs7:35": "{}<br>",
    "uvs7:36": "{}</p>",
    "uvs7:37": "<p>{}<br>",
    "uvs7:38": "{}<br>",
    "uvs7:39": "{}<br>",
    "uvs7:40": "{}<br>",
    "uvs7:41": "{}<br>",
    "uvs7:42": "{}</p>",
    "uvs7:43": "<p>{}<br>",
    "uvs7:44": "{}<br>",
    "uvs7:45": "{}<br>",
    "uvs7:46": "{}</p>",
    "uvs7:47": "<p>{}<br>",
    "uvs7:48": "{}<br>",
    "uvs7:49": "{}<br>",
    "uvs7:50": "{}</p>",
    "uvs7:51": "<p>{}<br>",
    "uvs7:52": "{}<br>",
    "uvs7:53": "{}<br>",
    "uvs7:54": "{}</p>",
    "uvs7:55": "<p>{}<br>",
    "uvs7:56": "{}<br>",
    "uvs7:57": "{}<br>",
    "uvs7:58": "{}<br>",
    "uvs7:59": "{}</p>",
    "uvs7:60": "<p class='endvagga'>{}</p>",
    "uvs7:61": "</blockquote>"
}