{
    "san-lo-bi-vb-ss18:0": [],
    "san-lo-bi-vb-ss18:1": [],
    "san-lo-bi-vb-ss18:2": [],
    "san-lo-bi-vb-ss18:3": [],
    "san-lo-bi-vb-ss18:4": [],
    "san-lo-bi-vb-ss18:5": [],
    "san-lo-bi-vb-ss18:6": [],
    "san-lo-bi-vb-ss18:7": [],
    "san-lo-bi-vb-ss18:8": [
        "sc1",
        "roth171"
    ],
    "san-lo-bi-vb-ss18:9": [
        "sc2"
    ],
    "san-lo-bi-vb-ss18:10": [],
    "san-lo-bi-vb-ss18:11": [
        "sc3"
    ],
    "san-lo-bi-vb-ss18:12": [],
    "san-lo-bi-vb-ss18:13": [],
    "san-lo-bi-vb-ss18:14": [],
    "san-lo-bi-vb-ss18:15": [],
    "san-lo-bi-vb-ss18:16": [],
    "san-lo-bi-vb-ss18:17": [],
    "san-lo-bi-vb-ss18:18": [],
    "san-lo-bi-vb-ss18:19": [],
    "san-lo-bi-vb-ss18:20": [
        "sc4"
    ],
    "san-lo-bi-vb-ss18:21": [],
    "san-lo-bi-vb-ss18:22": [],
    "san-lo-bi-vb-ss18:23": [],
    "san-lo-bi-vb-ss18:24": [],
    "san-lo-bi-vb-ss18:25": [],
    "san-lo-bi-vb-ss18:26": [
        "sc5"
    ],
    "san-lo-bi-vb-ss18:27": [
        "sc6"
    ],
    "san-lo-bi-vb-ss18:28": [],
    "san-lo-bi-vb-ss18:29": [
        "sc7"
    ]
}