{
    "uvs10:0": {},
    "uvs10:1": {},
    "uvs10:2": {},
    "uvs10:3": {},
    "uvs10:4": {},
    "uvs10:5": {},
    "uvs10:6": {},
    "uvs10:7": {},
    "uvs10:8": {
        "supplied": [
            "ra",
            "dh"
        ],
        "gap": [
            ". ."
        ]
    },
    "uvs10:9": {
        "supplied": [
            "dha",
            "e",
            "a",
            "ṣa-p",
            "a-"
        ],
        "unclear": [
            "r",
            "t"
        ]
    },
    "uvs10:10": {
        "supplied": [
            "śastāḥ"
        ]
    },
    "uvs10:11": {
        "gap": [
            ". . . . . . . . . ."
        ]
    },
    "uvs10:12": {
        "gap": [
            ". . . . . . . . . . ."
        ]
    },
    "uvs10:13": {
        "gap": [
            ". . . . . . . . . . . ."
        ]
    },
    "uvs10:14": {
        "gap": [
            ". . . . . . . . . . ."
        ]
    },
    "uvs10:15": {
        "gap": [
            ". . ."
        ],
        "supplied": [
            "dā",
            "aṁ"
        ],
        "unclear": [
            "a",
            "ā"
        ]
    },
    "uvs10:16": {
        "supplied": [
            "ti"
        ],
        "gap": [
            ". . . . ."
        ]
    },
    "uvs10:17": {
        "gap": [
            ". . . . . . . . . . ."
        ]
    },
    "uvs10:18": {
        "gap": [
            ". . . . . . . . . . ."
        ]
    },
    "uvs10:19": {
        "supplied": [
            "sat",
            "aṁ hi vai svād"
        ],
        "unclear": [
            "u"
        ]
    },
    "uvs10:20": {
        "supplied": [
            "ṁ"
        ]
    },
    "uvs10:21": {
        "unclear": [
            "j",
            "a"
        ],
        "supplied": [
            "ī",
            "i",
            "ā",
            "āṁ"
        ],
        "gap": [
            ". ."
        ]
    },
    "uvs10:22": {},
    "uvs10:23": {},
    "uvs10:24": {
        "unclear": [
            "ā"
        ],
        "supplied": [
            "e",
            "va"
        ]
    },
    "uvs10:25": {
        "supplied": [
            "aṁ",
            "yajati"
        ],
        "unclear": [
            "t"
        ]
    },
    "uvs10:26": {
        "gap": [
            ". . . .",
            ". . . ."
        ]
    },
    "uvs10:27": {
        "gap": [
            ". . . .",
            ". . . ."
        ]
    },
    "uvs10:28": {
        "gap": [
            ". . . .",
            ". . . ."
        ]
    },
    "uvs10:29": {
        "gap": [
            ". . . .",
            ". . . ."
        ]
    },
    "uvs10:30": {
        "supplied": [
            "i"
        ]
    },
    "uvs10:31": {
        "supplied": [
            "ā",
            "lañ ca"
        ]
    },
    "uvs10:32": {
        "gap": [
            ". . . .",
            ". . . ."
        ]
    },
    "uvs10:33": {
        "gap": [
            ". . . .",
            ". . . ."
        ]
    },
    "uvs10:34": {
        "gap": [
            ". . . .",
            ". . . ."
        ]
    },
    "uvs10:35": {
        "gap": [
            ". . . .",
            ". . . ."
        ]
    },
    "uvs10:36": {
        "gap": [
            ". . . .",
            ". . . ."
        ]
    },
    "uvs10:37": {
        "unclear": [
            "n",
            "n",
            "v",
            "t"
        ],
        "supplied": [
            "ra"
        ]
    },
    "uvs10:38": {
        "unclear": [
            "t",
            "t",
            "t",
            "v",
            "p",
            "j"
        ],
        "supplied": [
            "ra",
            "r",
            "ū",
            "yat"
        ]
    },
    "uvs10:39": {},
    "uvs10:40": {
        "gap": [
            ". . . .",
            ". . . ."
        ]
    },
    "uvs10:41": {
        "gap": [
            ". . . .",
            ". . . ."
        ]
    },
    "uvs10:42": {
        "gap": [
            ". . . .",
            ". . . ."
        ]
    },
    "uvs10:43": {
        "gap": [
            ". . . .",
            ". . . ."
        ]
    },
    "uvs10:44": {
        "gap": [
            ". . . .",
            ". . . ."
        ]
    },
    "uvs10:45": {},
    "uvs10:46": {},
    "uvs10:47": {},
    "uvs10:48": {
        "supplied": [
            "a",
            "āt",
            "a"
        ],
        "gap": [
            ". . .",
            ".",
            "."
        ]
    },
    "uvs10:49": {
        "gap": [
            ". . . .",
            ". . . ."
        ]
    },
    "uvs10:50": {
        "gap": [
            ". . . .",
            ". . . ."
        ]
    },
    "uvs10:51": {
        "gap": [
            ". . . .",
            ". . . ."
        ]
    },
    "uvs10:52": {
        "gap": [
            ". . ."
        ]
    },
    "uvs10:53": {},
    "uvs10:54": {
        "unclear": [
            "t"
        ],
        "supplied": [
            "u",
            "ṁ"
        ]
    },
    "uvs10:55": {
        "supplied": [
            "aḥ"
        ]
    },
    "uvs10:56": {
        "supplied": [
            "ṁ"
        ]
    },
    "uvs10:57": {
        "supplied": [
            "i"
        ]
    },
    "uvs10:58": {
        "unclear": [
            "r-",
            "-y"
        ],
        "gap": [
            ".",
            ". ."
        ]
    },
    "uvs10:59": {
        "gap": [
            ". . . .",
            ". . . ."
        ]
    },
    "uvs10:60": {},
    "uvs10:61": {},
    "uvs10:62": {},
    "uvs10:63": {},
    "uvs10:64": {},
    "uvs10:65": {
        "supplied": [
            "ṁ"
        ],
        "unclear": [
            "c"
        ]
    },
    "uvs10:66": {
        "supplied": [
            "rmma-śraddhā"
        ]
    },
    "uvs10:67": {}
}